{"kind":"identitytoolkit#DownloadAccountResponse","users":[{"localId":"q7SUosrcVeX213Uy2uijYZmCbXT3","createdAt":"1651064288990","lastLoginAt":"1651064288989","displayName":"","photoUrl":"","passwordHash":"fakeHash:salt=fakeSaltVVp75LFDwin6ATUB3jVI:password=Hostme@2022","salt":"fakeSaltVVp75LFDwin6ATUB3jVI","passwordUpdatedAt":1651173010178,"providerUserInfo":[{"providerId":"password","email":"testchat@gmail.com","federatedId":"testchat@gmail.com","rawId":"testchat@gmail.com","displayName":"","photoUrl":""}],"validSince":"1651173010","email":"testchat@gmail.com","emailVerified":false,"disabled":false},{"localId":"twLMR1WN7wCqQBmnChMvoSmx3jP9","createdAt":"1648633912672","lastLoginAt":"1649092471097","passwordHash":"fakeHash:salt=fakeSaltbdRHwR4t6TyOlstxEvdr:password=fakePassword1!","salt":"fakeSaltbdRHwR4t6TyOlstxEvdr","passwordUpdatedAt":1651173010178,"providerUserInfo":[{"providerId":"password","email":"testlogin@gmail.com","federatedId":"testlogin@gmail.com","rawId":"testlogin@gmail.com"}],"validSince":"1651173010","email":"testlogin@gmail.com","emailVerified":false,"disabled":false}]}